Metadata-Version: 2.1
Name: pytest-yc-bugtracker
Version: 0.0.1
Summary: Yandex Bug Tracker plugin for pytest
Home-page: https://github.com/PlagerX-Group/pytest-yc-tracker
Author: Matveev K.A.
Author-email: matveevkirill@internet.ru
License: Apache 2.0
Keywords: pytest-yc-bugtracker
Classifier: Development Status :: 1 - Planning
Classifier: Framework :: Pytest
Classifier: Intended Audience :: Developers
Classifier: License :: OSI Approved :: Apache Software License
Classifier: Topic :: Software Development :: Quality Assurance
Classifier: Programming Language :: Python :: 3 :: Only
Classifier: Programming Language :: Python :: 3.9
Requires-Python: >=3.9
License-File: LICENSE.rst
